odata/__init__.py
odata/odata.py
flask_smorest_sqlalchemy_odata-0.2.7.dist-info/LICENSE
flask_smorest_sqlalchemy_odata-0.2.7.dist-info/METADATA
flask_smorest_sqlalchemy_odata-0.2.7.dist-info/WHEEL
flask_smorest_sqlalchemy_odata-0.2.7.dist-info/top_level.txt
flask_smorest_sqlalchemy_odata-0.2.7.dist-info/RECORD
