Metadata-Version: 2.1
Name: flask-smorest-sqlalchemy-odata
Version: 0.2.7
Summary: Odata filtering and sorting with flask-smorest
Home-page: https://github.com/cknolla/flask-smorest-sqlalchemy-odata
Author: Casey Knolla
Author-email: cknolla@gmail.com
License: MIT
Requires-Python: >=3.9
License-File: LICENSE
Requires-Dist: apispec (>=5.1.0)
Requires-Dist: Flask (>=2.0.0)
Requires-Dist: flask-smorest (>=0.35.0)
Requires-Dist: Flask-SQLAlchemy (>=2.5.1)
Requires-Dist: marshmallow (>=3.14.1)
Requires-Dist: marshmallow-sqlalchemy (>=0.27.0)
Requires-Dist: sqlalchemy (>=1.4.0)
Requires-Dist: stringcase (>=1.2.0)
Requires-Dist: webargs (>=8.0.0)
Requires-Dist: Werkzeug (>=2.0.0)
